<!--?xml version="1.0" encoding="UTF-8" ?-->
<!--   Fuel gauging Configuration File -->
<!--   Intel Corporation 2013-2014  -->
<!-- FG config for XPower PMIC -->
<xpwr_config>
<cap1>0x8A</cap1>
<cap0>0x31</cap0>
<rdc1>0x80</rdc1>
<rdc0>0x89</rdc0>
<curve0>0x0</curve0>
<curve1>0x0</curve1>
<curve2>0x0</curve2>
<curve3>0x0</curve3>
<curve4>0x0</curve4>
<curve5>0x0</curve5>
<curve6>0x1</curve6>
<curve7>0x2</curve7>
<curve8>0x2</curve8>
<curve9>0x4</curve9>
<curve10>0x3</curve10>
<curve11>0xC</curve11>
<curve12>0x14</curve12>
<curve13>0x20</curve13>
<curve14>0x2A</curve14>
<curve15>0x2D</curve15>
<curve16>0x31</curve16>
<curve17>0x34</curve17>
<curve18>0x38</curve18>
<curve19>0x3D</curve19>
<curve20>0x42</curve20>
<curve21>0x45</curve21>
<curve22>0x49</curve22>
<curve23>0x4C</curve23>
<curve24>0x50</curve24>
<curve25>0x53</curve25>
<curve26>0x55</curve26>
<curve27>0x56</curve27>
<curve28>0x5A</curve28>
<curve29>0x5D</curve29>
<curve30>0x61</curve30>
<curve31>0x64</curve31>
</xpwr_config>
